MANIFEST.in
setup.py
provy/__init__.py
provy/console.py
provy.egg-info/PKG-INFO
provy.egg-info/SOURCES.txt
provy.egg-info/dependency_links.txt
provy.egg-info/entry_points.txt
provy.egg-info/requires.txt
provy.egg-info/top_level.txt
provy/core/__init__.py
provy/core/errors.py
provy/core/roles.py
provy/core/runner.py
provy/core/utils.py
provy/more/__init__.py
provy/more/base/__init__.py
provy/more/base/database/__init__.py
provy/more/base/database/postgresql.py
provy/more/centos/__init__.py
provy/more/centos/database/__init__.py
provy/more/centos/database/mysql.py
provy/more/centos/database/postgresql.py
provy/more/centos/messaging/__init__.py
provy/more/centos/messaging/rabbitmq.py
provy/more/centos/networking/__init__.py
provy/more/centos/networking/hosts.py
provy/more/centos/package/__init__.py
provy/more/centos/package/pip.py
provy/more/centos/package/yum.py
provy/more/centos/users/__init__.py
provy/more/centos/users/user.py
provy/more/centos/utils/__init__.py
provy/more/centos/utils/hostname.py
provy/more/centos/vcs/__init__.py
provy/more/centos/vcs/git.py
provy/more/debian/__init__.py
provy/more/debian/cache/__init__.py
provy/more/debian/cache/memcached.py
provy/more/debian/cache/varnish.py
provy/more/debian/cache/templates/memcached.conf.template
provy/more/debian/database/__init__.py
provy/more/debian/database/mongodb.py
provy/more/debian/database/mysql.py
provy/more/debian/database/postgresql.py
provy/more/debian/database/redis.py
provy/more/debian/monitoring/__init__.py
provy/more/debian/monitoring/supervisor.py
provy/more/debian/monitoring/templates/supervisord.conf.template
provy/more/debian/monitoring/templates/supervisord.init.template
provy/more/debian/networking/__init__.py
provy/more/debian/networking/hosts.py
provy/more/debian/package/__init__.py
provy/more/debian/package/aptitude.py
provy/more/debian/package/gem.py
provy/more/debian/package/npm.py
provy/more/debian/package/pip.py
provy/more/debian/package/virtualenv.py
provy/more/debian/programming/__init__.py
provy/more/debian/programming/nodejs.py
provy/more/debian/programming/php.py
provy/more/debian/programming/ruby.py
provy/more/debian/security/__init__.py
