Metadata-Version: 1.1
Name: provy
Version: 0.6.1
Summary: provy is an easy-to-use server provisioning tool.
Home-page: http://provy.me
Author: Bernardo Heynemann
Author-email: heynemann@gmail.com
License: MIT
Keywords: provisioning devops infrastructure server
Platform: UNKNOWN
Classifier: Development Status :: 3 - Alpha
Classifier: Intended Audience :: Developers
Classifier: License :: OSI Approved :: MIT License
Classifier: Natural Language :: English
Classifier: Operating System :: MacOS
Classifier: Operating System :: Microsoft :: Windows
Classifier: Operating System :: POSIX :: Linux
Classifier: Programming Language :: Python :: 2.6
Classifier: Topic :: System :: Installation/Setup
